README.md
setup.py
test/test_numbers.py
test/test_strings.py
typechecks/__init__.py
typechecks.egg-info/PKG-INFO
typechecks.egg-info/SOURCES.txt
typechecks.egg-info/dependency_links.txt
typechecks.egg-info/top_level.txt