Metadata-Version: 1.1
Name: typechecks
Version: 0.1.0
Summary: Helper functions for runtime type checking
Home-page: https://github.com/openvax/typechecks
Author: Tim O'Donnell
Author-email: tim.odonnell@mssm.edu
License: http://www.apache.org/licenses/LICENSE-2.0.html
Platform: UNKNOWN
Classifier: Development Status :: 3 - Alpha
Classifier: Environment :: Console
Classifier: Operating System :: OS Independent
Classifier: Intended Audience :: Developers
Classifier: License :: OSI Approved :: Apache Software License
Classifier: Programming Language :: Python
